claude_on_the_go/__init__.py
claude_on_the_go/cli.py
claude_on_the_go-1.0.0.dist-info/licenses/LICENSE
client/README.md
client/__init__.py
client/pwa/generate-icons.html
client/pwa/manifest.json
client/pwa/offline.html
client/pwa/sw.js
core/README.md
core/__init__.py
core/config.py
core/pty_manager.py
core/session_store.py
integrations/README.md
integrations/__init__.py
integrations/notifications.py
integrations/prompt_detector.py
legacy/README.md
legacy/launcher.py
legacy/backend/__init__.py
legacy/backend/app.py
legacy/backend/claude_wrapper.py
legacy/backend/clipboard_manager.py
legacy/backend/config.py
legacy/backend/ghostty_parser.py
legacy/backend/network_utils.py
legacy/backend/session_manager.py
legacy/backend/.claude/settings.local.json
legacy/backend/parsers/__init__.py
legacy/backend/parsers/alacritty_parser.py
legacy/backend/parsers/default_theme.py
legacy/backend/parsers/ghostty_parser.py
legacy/backend/parsers/hyper_parser.py
legacy/backend/parsers/iterm2_parser.py
legacy/backend/parsers/kitty_parser.py
legacy/backend/parsers/terminal_app_parser.py
legacy/backend/parsers/terminal_detector.py
legacy/backend/parsers/warp_parser.py
legacy/backend/parsers/windows_terminal_parser.py
legacy/backend/security/__init__.py
legacy/backend/security/auth.py
legacy/backend/security/rate_limiter.py
legacy/backend/security/sanitizer.py
legacy/backend/security/validator.py
legacy/frontend/index.html
legacy/frontend/manifest.json
legacy/frontend/offline.html
legacy/frontend/serve.py
legacy/frontend/style.css
legacy/frontend/sw.js
legacy/frontend/terminal.js
legacy/frontend/icons/apple-touch-icon.png
legacy/frontend/icons/icon-128x128.png
legacy/frontend/icons/icon-144x144.png
legacy/frontend/icons/icon-152x152.png
legacy/frontend/icons/icon-16x16.png
legacy/frontend/icons/icon-192x192.png
legacy/frontend/icons/icon-32x32.png
legacy/frontend/icons/icon-384x384.png
legacy/frontend/icons/icon-512x512.png
legacy/frontend/icons/icon-72x72.png
legacy/frontend/icons/icon-96x96.png
scripts/__init__.py
claude_on_the_go-1.0.0.dist-info/METADATA
claude_on_the_go-1.0.0.dist-info/WHEEL
claude_on_the_go-1.0.0.dist-info/entry_points.txt
claude_on_the_go-1.0.0.dist-info/top_level.txt
claude_on_the_go-1.0.0.dist-info/RECORD
