Metadata-Version: 2.4
Name: claude-on-the-go
Version: 1.0.0
Summary: Access Claude Code CLI from your mobile device over WiFi
Author-email: Matthew Jamison <99699313+MatthewJamisonJS@users.noreply.github.com>
Maintainer-email: Matthew Jamison <99699313+MatthewJamisonJS@users.noreply.github.com>
License: MIT
Project-URL: Homepage, https://github.com/MatthewJamisonJS/claude-on-the-go
Project-URL: Documentation, https://github.com/MatthewJamisonJS/claude-on-the-go#readme
Project-URL: Repository, https://github.com/MatthewJamisonJS/claude-on-the-go
Project-URL: Bug Reports, https://github.com/MatthewJamisonJS/claude-on-the-go/issues
Project-URL: Source Code, https://github.com/MatthewJamisonJS/claude-on-the-go
Keywords: claude,terminal,mobile,websocket,pwa,cli
Classifier: Development Status :: 4 - Beta
Classifier: Intended Audience :: Developers
Classifier: Topic :: Software Development :: User Interfaces
Classifier: Topic :: Terminals
Classifier: License :: OSI Approved :: MIT License
Classifier: Programming Language :: Python :: 3
Classifier: Programming Language :: Python :: 3.9
Classifier: Programming Language :: Python :: 3.10
Classifier: Programming Language :: Python :: 3.11
Classifier: Programming Language :: Python :: 3.12
Classifier: Programming Language :: Python :: 3.13
Classifier: Operating System :: MacOS :: MacOS X
Classifier: Operating System :: POSIX :: Linux
Classifier: Environment :: Web Environment
Classifier: Framework :: FastAPI
Requires-Python: >=3.9
License-File: LICENSE
Requires-Dist: fastapi>=0.118.0
Requires-Dist: uvicorn[standard]>=0.37.0
Requires-Dist: websockets>=15.0
Requires-Dist: pexpect>=4.9.0
Requires-Dist: qrcode[pil]>=8.0
Requires-Dist: PyYAML>=6.0
Requires-Dist: pydantic-settings>=2.11.0
Requires-Dist: httpx>=0.27.0
Provides-Extra: dev
Requires-Dist: pytest>=8.0; extra == "dev"
Requires-Dist: pytest-asyncio>=0.23.0; extra == "dev"
Requires-Dist: pytest-cov>=4.0; extra == "dev"
Requires-Dist: psutil>=5.9.0; extra == "dev"
Requires-Dist: mypy>=1.0; extra == "dev"
Requires-Dist: black>=23.0; extra == "dev"
Requires-Dist: ruff>=0.1.0; extra == "dev"
Requires-Dist: build>=1.0.0; extra == "dev"
Requires-Dist: twine>=4.0.0; extra == "dev"
Provides-Extra: security
Requires-Dist: safety>=2.3.0; extra == "security"
Requires-Dist: bandit>=1.8.0; extra == "security"
Dynamic: license-file
